dockpysdk/__init__.py
dockpysdk/build_formatter.py
dockpysdk/client.py
dockpysdk/compose_dependencies.py
dockpysdk/compose_orchestrator.py
dockpysdk/compose_parser.py
dockpysdk/containers.py
dockpysdk/http_client.py
dockpysdk/images.py
dockpysdk/models.py
dockpysdk/networks.py
dockpysdk/transport.py
dockpysdk/volumes.py
dockpy_sdk-0.0.1rc5.dist-info/METADATA
dockpy_sdk-0.0.1rc5.dist-info/WHEEL
dockpy_sdk-0.0.1rc5.dist-info/RECORD
