Metadata-Version: 2.4
Name: dockpy-sdk
Version: 0.0.1rc5
Summary: dockpy-sdk - Docker SDK with async operations
Project-URL: Issue Tracker, https://github.com/BackBenchDevs/dockpy/issues
Project-URL: Source Code, https://gerrit.bbdevs.com/dockpy
Author-email: BBDevs <dev@bbdevs.com>
License: Apache-2.0
Keywords: api,async,docker,httpx,sdk
Classifier: Development Status :: 3 - Alpha
Classifier: Environment :: Console
Classifier: Intended Audience :: Developers
Classifier: License :: OSI Approved :: Apache Software License
Classifier: Operating System :: OS Independent
Classifier: Programming Language :: Python :: 3
Classifier: Programming Language :: Python :: 3.10
Classifier: Programming Language :: Python :: 3.11
Classifier: Programming Language :: Python :: 3.12
Classifier: Topic :: Software Development :: Libraries :: Python Modules
Classifier: Topic :: System :: Systems Administration
Requires-Python: >=3.10
Requires-Dist: anyio>=4.0.0
Requires-Dist: dockpy-core
Requires-Dist: httpx>=0.25.0
Requires-Dist: ruyaml>=0.91.0
Provides-Extra: dev
Requires-Dist: pytest-asyncio>=0.21.1; extra == 'dev'
Requires-Dist: pytest-cov>=4.1.0; extra == 'dev'
Requires-Dist: pytest>=7.4.3; extra == 'dev'
Requires-Dist: respx>=0.20.0; extra == 'dev'
